cli.py
dctap2shacl.py
dctap2shacl-0.1.1.dist-info/METADATA
dctap2shacl-0.1.1.dist-info/WHEEL
dctap2shacl-0.1.1.dist-info/entry_points.txt
dctap2shacl-0.1.1.dist-info/top_level.txt
dctap2shacl-0.1.1.dist-info/RECORD
