Metadata-Version: 2.4
Name: dctap2shacl
Version: 0.1.1
Summary: BIBFRAME Interoperability Group code for transforming DCTap tsv files into SHACL
Requires-Python: >=3.12
Requires-Dist: rdflib>=7.4.0
